k_logger/__init__.py
k_logger/logger.py
k_logging-1.0.0.dist-info/licenses/LICENSE
k_logging-1.0.0.dist-info/METADATA
k_logging-1.0.0.dist-info/WHEEL
k_logging-1.0.0.dist-info/top_level.txt
k_logging-1.0.0.dist-info/RECORD
