Metadata-Version: 2.4
Name: k-logging
Version: 1.0.0
Summary: Korean-friendly logging utility with abbreviated levels and Korean timezone
Home-page: https://github.com/june-oh/k-logger
Author: june-oh
Author-email: june-oh <ohjs@sogang.ac.kr>
License: MIT
Project-URL: Homepage, https://github.com/june-oh/k-logger
Project-URL: Issues, https://github.com/june-oh/k-logger/issues
Keywords: logging,korean,timezone,kst,loguru,abbreviated,simple
Classifier: Development Status :: 3 - Alpha
Classifier: Intended Audience :: Developers
Classifier: License :: OSI Approved :: MIT License
Classifier: Operating System :: OS Independent
Classifier: Programming Language :: Python :: 3
Classifier: Programming Language :: Python :: 3.7
Classifier: Programming Language :: Python :: 3.8
Classifier: Programming Language :: Python :: 3.9
Classifier: Programming Language :: Python :: 3.10
Classifier: Programming Language :: Python :: 3.11
Classifier: Programming Language :: Python :: 3.12
Classifier: Topic :: System :: Logging
Classifier: Topic :: Software Development :: Libraries :: Python Modules
Classifier: Natural Language :: Korean
Requires-Python: >=3.7
License-File: LICENSE
Requires-Dist: loguru>=0.6.0
Requires-Dist: pytz>=2021.1
Provides-Extra: dev
Requires-Dist: pytest>=6.0; extra == "dev"
Requires-Dist: black; extra == "dev"
Requires-Dist: flake8; extra == "dev"
Requires-Dist: mypy; extra == "dev"
Dynamic: author
Dynamic: home-page
Dynamic: license-file
Dynamic: requires-python
